{
  "uuid": "011a68f2-cbfc-4566-8b84-073cafff64e3",
  "path": "/usr/lib/python3/dist-packages/jinja2/__pycache__/optimizer.cpython-312.pyc",
  "size": 2651,
  "modified": "2025-05-09T05:11:38.952943587Z",
  "created": "2025-05-09T05:11:38.952943587Z",
  "sha256_hash": "7e2fb918bed72d880747140d449e20b6abd7b2783c932a0d675fa034c145f213",
  "file_type": {
    "Other": "pyc"
  },
  "permissions": 33188,
  "is_executable": true,
  "is_signed": false,
  "code_signature": null,
  "bundle_info": null,
  "scan_timestamp": "2025-06-01T18:45:26.465882049Z"
}