{
  "uuid": "070c5324-65f6-4807-bb30-2bff1c1c6cfa",
  "path": "/usr/lib/aspell/en_GB-ise-w_accents.multi",
  "size": 110,
  "modified": "2020-12-08T01:19:37Z",
  "created": "2025-05-09T05:07:21.014880380Z",
  "sha256_hash": "fc08d9718e071b044e3b8ba49c5a88666311dcb2f9f427fa281e2d62fda946f0",
  "file_type": {
    "Other": "multi"
  },
  "permissions": 33188,
  "is_executable": true,
  "is_signed": false,
  "code_signature": null,
  "bundle_info": null,
  "scan_timestamp": "2025-06-01T18:45:55.297033257Z"
}