{
  "uuid": "07830979-f954-48fd-ac24-10f1f4618175",
  "path": "/usr/lib/python3.12/test/test_type_annotations.py",
  "size": 6383,
  "modified": "2025-02-04T14:48:35Z",
  "created": "2025-05-28T17:29:48.044551079Z",
  "sha256_hash": "3076513c7cdbd80d6268aef3f641a474cab63a1fc1318e1a65fcc3271af81157",
  "file_type": "Script",
  "permissions": 33188,
  "is_executable": true,
  "is_signed": false,
  "code_signature": null,
  "bundle_info": null,
  "scan_timestamp": "2025-06-01T18:46:03.805336642Z"
}