{
  "uuid": "0c2344bf-f5cf-48d1-9fe7-8b5d34d4b536",
  "path": "/lib/gcc/x86_64-linux-gnu/13/adainclude/s-objrea.adb",
  "size": 67352,
  "modified": "2024-05-21T07:47:38Z",
  "created": "2025-05-29T11:24:15.080344736Z",
  "sha256_hash": "1f866d8518c66753c8ee487c29f956f323160f6dd960b8cacc56c57d1ed6c19e",
  "file_type": {
    "Other": "adb"
  },
  "permissions": 33188,
  "is_executable": false,
  "is_signed": false,
  "code_signature": null,
  "bundle_info": null,
  "scan_timestamp": "2025-06-01T18:46:56.987745030Z"
}