{
  "uuid": "0f377ab1-77d8-4363-8e9a-f04d7dac1a42",
  "path": "/usr/lib/libreoffice/share/numbertext/ro.sor",
  "size": 3293,
  "modified": "2025-05-05T15:20:55Z",
  "created": "2025-05-09T05:11:17.342273467Z",
  "sha256_hash": "5ca0f02a3f2557a927faac138d03427aef90a678d33cb5787c377514ae7626ba",
  "file_type": {
    "Other": "sor"
  },
  "permissions": 33188,
  "is_executable": true,
  "is_signed": false,
  "code_signature": null,
  "bundle_info": null,
  "scan_timestamp": "2025-06-01T18:45:41.668933582Z"
}