{
  "uuid": "1435681f-6734-49ca-ac62-0968d3f2a00c",
  "path": "/usr/lib/gcc/x86_64-linux-gnu/13/adainclude/s-pack75.ads",
  "size": 3227,
  "modified": "2024-05-21T07:47:38Z",
  "created": "2025-05-29T11:24:15.085344667Z",
  "sha256_hash": "1881fd86a20388e2cd2bf5bca1e7f79dd0ef3d2ec59ab82e990b4b50191f0f14",
  "file_type": {
    "Other": "ads"
  },
  "permissions": 33188,
  "is_executable": true,
  "is_signed": false,
  "code_signature": null,
  "bundle_info": null,
  "scan_timestamp": "2025-06-01T18:45:51.274322329Z"
}