{
  "uuid": "16a7e4ad-14c6-4dd9-b976-ca26a197ca16",
  "path": "/usr/lib/python3.12/test/__pycache__/test_unicode_file.cpython-312.pyc",
  "size": 8578,
  "modified": "2025-05-28T17:29:54.915460860Z",
  "created": "2025-05-28T17:29:54.915460860Z",
  "sha256_hash": "2a26f5dfcbd2f9bd6c64d9a99d5eb102dc133a499b590d61d30fc90294507dfe",
  "file_type": {
    "Other": "pyc"
  },
  "permissions": 33188,
  "is_executable": true,
  "is_signed": false,
  "code_signature": null,
  "bundle_info": null,
  "scan_timestamp": "2025-06-01T18:46:03.323211454Z"
}