{
  "uuid": "1a88a7d6-8567-4770-8bcf-b606328a7ea7",
  "path": "/usr/lib/python3/dist-packages/apport/__pycache__/__init__.cpython-312.pyc",
  "size": 956,
  "modified": "2025-05-30T21:04:55.742545587Z",
  "created": "2025-05-30T21:04:55.742545587Z",
  "sha256_hash": "9a64d759a12273cb6a5dfe498baf08f8f12f6f5e57518db39bc8345c7a1af60f",
  "file_type": {
    "Other": "pyc"
  },
  "permissions": 33188,
  "is_executable": true,
  "is_signed": false,
  "code_signature": null,
  "bundle_info": null,
  "scan_timestamp": "2025-06-01T18:45:26.068605262Z"
}