{
  "uuid": "20ba11d7-ae35-42f0-bfef-0c80e44ef2aa",
  "path": "/lib/python3/dist-packages/gyp/generator/make.py",
  "size": 92592,
  "modified": "2022-07-16T12:04:27Z",
  "created": "2025-05-13T14:32:17.132697827Z",
  "sha256_hash": "ce640cfd44fa85ecac186a1f9f84da27da15cb842019cfb336b7b6217b890240",
  "file_type": "Script",
  "permissions": 33188,
  "is_executable": false,
  "is_signed": false,
  "code_signature": null,
  "bundle_info": null,
  "scan_timestamp": "2025-06-01T18:46:34.445311314Z"
}