{
  "uuid": "218098ac-d3ac-4cbb-a627-22ea9a76c336",
  "path": "/lib/python3/dist-packages/LanguageSelector/macros.py",
  "size": 5392,
  "modified": "2024-04-19T01:27:07Z",
  "created": "2025-05-09T05:07:26.407798086Z",
  "sha256_hash": "594ef36d767e7ea140173488605843c235dfb350afdb317c355e90a0cf16766a",
  "file_type": "Script",
  "permissions": 33188,
  "is_executable": false,
  "is_signed": false,
  "code_signature": null,
  "bundle_info": null,
  "scan_timestamp": "2025-06-01T18:46:33.625624041Z"
}