{
  "uuid": "24b35860-18f9-4296-9f39-dd0f5edddc21",
  "path": "/lib/firmware/qca/hpnv21g.baa.zst",
  "size": 2790,
  "modified": "2025-04-17T06:14:44Z",
  "created": "2025-05-29T10:40:08.967535787Z",
  "sha256_hash": "a517b9144a1ea74bfef16bde93580c807eea6485b3bd7cbf2c00627e82e705d2",
  "file_type": {
    "Other": "zst"
  },
  "permissions": 33188,
  "is_executable": false,
  "is_signed": false,
  "code_signature": null,
  "bundle_info": null,
  "scan_timestamp": "2025-06-01T18:47:07.163839401Z"
}