{
  "uuid": "260d3876-a473-4e00-b4c9-d3797c7fc095",
  "path": "/usr/lib/libreoffice/share/gallery/bullets/orgball.gif",
  "size": 104,
  "modified": "2024-10-29T11:14:30Z",
  "created": "2025-05-09T05:11:17.322273772Z",
  "sha256_hash": "0159a213c2b2d4c8ba2bad92d8d36ebc523549643de02579df0582ead44e8180",
  "file_type": {
    "Other": "gif"
  },
  "permissions": 33188,
  "is_executable": true,
  "is_signed": false,
  "code_signature": null,
  "bundle_info": null,
  "scan_timestamp": "2025-06-01T18:45:41.764269140Z"
}