{
  "uuid": "298f7ade-87a1-4e5d-aed7-80b841011829",
  "path": "/usr/lib/x86_64-linux-gnu/perl/5.38.2/endian.ph",
  "size": 3627,
  "modified": "2025-04-08T12:47:54Z",
  "created": "2025-05-09T05:10:56.559590701Z",
  "sha256_hash": "c9447bbf738bdefe89f200ccf60fdd60a9dc1431c47f12290178671bff7f8f3f",
  "file_type": {
    "Other": "ph"
  },
  "permissions": 33188,
  "is_executable": true,
  "is_signed": false,
  "code_signature": null,
  "bundle_info": null,
  "scan_timestamp": "2025-06-01T18:46:12.679113387Z"
}