{
  "uuid": "310ffdc6-4e56-42cb-a26c-d2dcf4343ef7",
  "path": "/usr/lib/llvm-18/include/clang/AST/DeclObjCCommon.h",
  "size": 1754,
  "modified": "2023-01-02T13:01:23Z",
  "created": "2025-05-12T13:34:31.517533740Z",
  "sha256_hash": "6435f9571dc1d5b8ebddc8b9ee05673971a5290c6eb302e6e0fab000e61ad270",
  "file_type": {
    "Other": "h"
  },
  "permissions": 33188,
  "is_executable": true,
  "is_signed": false,
  "code_signature": null,
  "bundle_info": null,
  "scan_timestamp": "2025-06-01T18:45:28.392148739Z"
}