{
  "uuid": "350f80a8-87a3-48db-8467-4bf89f1cc177",
  "path": "/usr/lib/x86_64-linux-gnu/gtk-2.0/include/gdkconfig.h",
  "size": 583,
  "modified": "2024-07-15T16:53:59Z",
  "created": "2025-05-29T11:16:08.321028314Z",
  "sha256_hash": "4cfd21bec8a1ba3fd5e646f383710361065a9ad8f91bf5c13e1a2bc94b1f324f",
  "file_type": {
    "Other": "h"
  },
  "permissions": 33188,
  "is_executable": true,
  "is_signed": false,
  "code_signature": null,
  "bundle_info": null,
  "scan_timestamp": "2025-06-01T18:46:18.304658214Z"
}