{
  "uuid": "404fa46b-d602-4d38-9c33-1326ca498ed3",
  "path": "/usr/lib/gcc/x86_64-linux-gnu/13/adainclude/s-pack42.ads",
  "size": 3895,
  "modified": "2024-05-21T07:47:38Z",
  "created": "2025-05-29T11:24:15.084344681Z",
  "sha256_hash": "7594a13b5476f3b27f54a91727c8b6ba44328b260d5b6255e2ff2c4738aebdb3",
  "file_type": {
    "Other": "ads"
  },
  "permissions": 33188,
  "is_executable": true,
  "is_signed": false,
  "code_signature": null,
  "bundle_info": null,
  "scan_timestamp": "2025-06-01T18:45:51.163651479Z"
}