{
  "uuid": "504a0d4f-c4e6-4273-a5a8-da741f04ce60",
  "path": "/usr/lib/python3/dist-packages/configobj-5.0.8.dist-info/top_level.txt",
  "size": 19,
  "modified": "2024-01-07T23:59:06Z",
  "created": "2025-05-09T05:07:26.726793219Z",
  "sha256_hash": "26268ec9c48fd0159b16530a4943652ae24a62874b27f582ae868cd607188c9b",
  "file_type": "Document",
  "permissions": 33188,
  "is_executable": true,
  "is_signed": false,
  "code_signature": null,
  "bundle_info": null,
  "scan_timestamp": "2025-06-01T18:45:26.119655391Z"
}