{
  "uuid": "55123599-627e-436a-8afa-69214a824b0a",
  "path": "/lib/systemd/user/org.gnome.SettingsDaemon.Keyboard.service",
  "size": 784,
  "modified": "2024-04-18T10:59:35Z",
  "created": "2025-05-09T05:07:28.306769109Z",
  "sha256_hash": "4a79a4824ef8515908de496f073e6481610e2c36143a41bd90381336f6fee6c9",
  "file_type": {
    "Other": "service"
  },
  "permissions": 33188,
  "is_executable": false,
  "is_signed": false,
  "code_signature": null,
  "bundle_info": null,
  "scan_timestamp": "2025-06-01T18:46:59.142075503Z"
}