{
  "uuid": "5764e5d5-0d87-4893-b02c-67be1698692d",
  "path": "/lib/grub/x86_64-efi/testspeed.mod",
  "size": 3568,
  "modified": "2025-03-17T13:20:09Z",
  "created": "2025-05-09T05:08:37.839707987Z",
  "sha256_hash": "c08628bc03f6edd1297eb12aab16fae6c08ff5b6a87d1d8429b18baac7ce8930",
  "file_type": {
    "Other": "mod"
  },
  "permissions": 33188,
  "is_executable": false,
  "is_signed": false,
  "code_signature": null,
  "bundle_info": null,
  "scan_timestamp": "2025-06-01T18:47:00.031473931Z"
}