{
  "uuid": "5a4c9472-931b-4f0f-a4fd-94c886df38e4",
  "path": "/lib/gcc/x86_64-linux-gnu/13/include/raointintrin.h",
  "size": 2941,
  "modified": "2024-09-04T14:44:14Z",
  "created": "2025-05-09T06:33:30.245389810Z",
  "sha256_hash": "53e6b0e7ee4227c977fb2b16556273c755d4a8eb9e13e04bf253de3c4df41749",
  "file_type": {
    "Other": "h"
  },
  "permissions": 33188,
  "is_executable": false,
  "is_signed": false,
  "code_signature": null,
  "bundle_info": null,
  "scan_timestamp": "2025-06-01T18:46:55.924013754Z"
}