{
  "uuid": "5e22e28d-4215-4401-a801-08dcaeb440ee",
  "path": "/lib/python3/dist-packages/snowballstemmer/__pycache__/hindi_stemmer.cpython-312.pyc",
  "size": 9557,
  "modified": "2025-05-13T14:31:47.502277483Z",
  "created": "2025-05-13T14:31:47.502277483Z",
  "sha256_hash": "df437d0e748326bcf491d0f819f2c8f93e3f2683f6302984c550883f725c68a4",
  "file_type": {
    "Other": "pyc"
  },
  "permissions": 33188,
  "is_executable": false,
  "is_signed": false,
  "code_signature": null,
  "bundle_info": null,
  "scan_timestamp": "2025-06-01T18:46:33.975869892Z"
}