{
  "uuid": "603340dc-8f31-4012-97bc-71658ce119b4",
  "path": "/usr/lib/x86_64-linux-gnu/samba/libsamba-modules-samba4.so.0",
  "size": 14568,
  "modified": "2024-04-08T14:49:25Z",
  "created": "2025-05-09T05:07:37.084635161Z",
  "sha256_hash": "675963088f12156b706e90c59aa967fd87e2937c8c8075b84fd70914878779a0",
  "file_type": {
    "Other": "0"
  },
  "permissions": 33188,
  "is_executable": true,
  "is_signed": false,
  "code_signature": null,
  "bundle_info": null,
  "scan_timestamp": "2025-06-01T18:46:24.375450213Z"
}