{
  "uuid": "61df1755-0aa9-428e-9350-df5a1c477d99",
  "path": "/usr/lib/gcc/x86_64-linux-gnu/13/adainclude/a-wtedit.adb",
  "size": 76970,
  "modified": "2024-05-21T07:47:38Z",
  "created": "2025-05-29T11:24:15.062344984Z",
  "sha256_hash": "4276639a329ec02c78489c0527d7a7726495ebfc6cd48da2d832229ebafb4922",
  "file_type": {
    "Other": "adb"
  },
  "permissions": 33188,
  "is_executable": true,
  "is_signed": false,
  "code_signature": null,
  "bundle_info": null,
  "scan_timestamp": "2025-06-01T18:45:50.888751915Z"
}