{
  "uuid": "6658ab11-2273-45b6-a054-0c4874d96a1b",
  "path": "/lib/google-cloud-sdk/lib/surface/logging/read.py",
  "size": 6497,
  "modified": "1980-01-01T08:00:00Z",
  "created": "2025-05-29T15:06:06.694932584Z",
  "sha256_hash": "48fe4ac8d2588a11f53a62ef1f3914f87a8a152c4a5296ee6d132d0cd28087c6",
  "file_type": "Script",
  "permissions": 33188,
  "is_executable": false,
  "is_signed": false,
  "code_signature": null,
  "bundle_info": null,
  "scan_timestamp": "2025-06-01T18:46:54.067787383Z"
}