{
  "uuid": "745087dd-9a04-4eaa-83e8-13ad65aa5165",
  "path": "/usr/lib/x86_64-linux-gnu/libsynctex.so.2.0.0",
  "size": 123832,
  "modified": "2024-03-31T08:27:34Z",
  "created": "2025-05-09T05:07:32.213709490Z",
  "sha256_hash": "9d811b987922ce896d662a7dce04dd008df7127babcd632a29449ecd29b0ae92",
  "file_type": {
    "Other": "0"
  },
  "permissions": 33188,
  "is_executable": true,
  "is_signed": false,
  "code_signature": null,
  "bundle_info": null,
  "scan_timestamp": "2025-06-01T18:46:14.454810197Z"
}