{
  "uuid": "7eecec67-bfb5-4080-977c-47523f77cb40",
  "path": "/usr/lib/python3.12/unittest/__pycache__/_log.cpython-312.pyc",
  "size": 4676,
  "modified": "2025-05-09T05:11:42.100895534Z",
  "created": "2025-05-09T05:11:42.100895534Z",
  "sha256_hash": "7be0fcbd36b2cba821810330c316d359d83ab9a18a0113baa654094d31634504",
  "file_type": {
    "Other": "pyc"
  },
  "permissions": 33188,
  "is_executable": true,
  "is_signed": false,
  "code_signature": null,
  "bundle_info": null,
  "scan_timestamp": "2025-06-01T18:46:04.704012336Z"
}