{
  "uuid": "7f7c4a14-e867-4ed2-96ca-de352fc25bf1",
  "path": "/lib/firmware/amdgpu/gc_10_3_6_pfp.bin.zst",
  "size": 14834,
  "modified": "2025-04-17T06:14:44Z",
  "created": "2025-05-29T10:40:08.394543723Z",
  "sha256_hash": "c8888fe0cde2a0663656fb7e908957038007450495a04e4d7fa437cf560d0b2a",
  "file_type": {
    "Other": "zst"
  },
  "permissions": 33188,
  "is_executable": false,
  "is_signed": false,
  "code_signature": null,
  "bundle_info": null,
  "scan_timestamp": "2025-06-01T18:47:05.061010521Z"
}