{
  "uuid": "8bc43234-862f-4b0e-87f8-835204d40f58",
  "path": "/usr/lib/modules/6.11.0-25-generic/kernel/crypto/crypto_simd.ko.zst",
  "size": 5663,
  "modified": "2025-04-15T12:48:48Z",
  "created": "2025-05-09T05:08:54.098459849Z",
  "sha256_hash": "a4e2235143c0e9b29479c7d3e93579cfb118bcba49144d1bdbaa04d7290bc5ea",
  "file_type": {
    "Other": "zst"
  },
  "permissions": 33188,
  "is_executable": true,
  "is_signed": false,
  "code_signature": null,
  "bundle_info": null,
  "scan_timestamp": "2025-06-01T18:45:54.023301837Z"
}