{
  "uuid": "8c12b383-f2d1-4400-9f7a-812ec6153941",
  "path": "/usr/lib/python3/dist-packages/gyp/__pycache__/easy_xml.cpython-312.pyc",
  "size": 6376,
  "modified": "2025-05-13T14:33:10.864728001Z",
  "created": "2025-05-13T14:33:10.864728001Z",
  "sha256_hash": "626dc6acbf5ce4bab22adec9cb50d4b1d23114fc04b5334dc920ba1bc05f92b8",
  "file_type": {
    "Other": "pyc"
  },
  "permissions": 33188,
  "is_executable": true,
  "is_signed": false,
  "code_signature": null,
  "bundle_info": null,
  "scan_timestamp": "2025-06-01T18:45:26.587179042Z"
}