{
  "uuid": "a01f6051-1e57-418b-9300-881bbe1b72bb",
  "path": "/usr/lib/firmware/cirrus/cs35l41-dsp1-spk-cali-103c8b63-r1.bin.zst",
  "size": 1052,
  "modified": "2025-04-17T06:14:44Z",
  "created": "2025-05-29T10:40:08.499542269Z",
  "sha256_hash": "15e927b5b7052f1a38dafb0bfa2c802883ccbffb982d6eb73d4be118b07cf1c5",
  "file_type": {
    "Other": "zst"
  },
  "permissions": 33188,
  "is_executable": true,
  "is_signed": false,
  "code_signature": null,
  "bundle_info": null,
  "scan_timestamp": "2025-06-01T18:46:02.369177948Z"
}