{
  "uuid": "a52ff388-0414-4ec1-93ed-9d142a0def7d",
  "path": "/usr/lib/x86_64-linux-gnu/perl/5.38.2/CORE/dosish.h",
  "size": 3691,
  "modified": "2025-04-08T12:47:54Z",
  "created": "2025-05-09T05:10:56.502591571Z",
  "sha256_hash": "e969465e80a45f9b84f6b5599b358c38b35bcf1486b0f9aac6f4963bc2cdf0a0",
  "file_type": {
    "Other": "h"
  },
  "permissions": 33188,
  "is_executable": true,
  "is_signed": false,
  "code_signature": null,
  "bundle_info": null,
  "scan_timestamp": "2025-06-01T18:46:12.555790445Z"
}