{
  "uuid": "a89ea05f-05c4-454b-919e-42230b306953",
  "path": "/usr/lib/x86_64-linux-gnu/icu/74.2/Makefile.inc",
  "size": 9771,
  "modified": "2024-08-09T02:33:20Z",
  "created": "2025-05-12T13:34:33.792503783Z",
  "sha256_hash": "726bb9cffcfed4c901edb5a333abf718643b14c07bcfb174cab0774b0ee9efbb",
  "file_type": {
    "Other": "inc"
  },
  "permissions": 33188,
  "is_executable": true,
  "is_signed": false,
  "code_signature": null,
  "bundle_info": null,
  "scan_timestamp": "2025-06-01T18:46:23.643189380Z"
}