{
  "uuid": "b1eca2a0-54e7-4ec6-9499-edb7503dbe3c",
  "path": "/usr/lib/x86_64-linux-gnu/samba/libgenrand-samba4.so.0",
  "size": 18664,
  "modified": "2024-04-08T14:49:25Z",
  "created": "2025-05-09T05:07:37.056635588Z",
  "sha256_hash": "c399830d4dd1759d1f8d9184ecccf7063ad82651d2143f7e1b21ce802f292789",
  "file_type": {
    "Other": "0"
  },
  "permissions": 33188,
  "is_executable": true,
  "is_signed": false,
  "code_signature": null,
  "bundle_info": null,
  "scan_timestamp": "2025-06-01T18:46:24.372220316Z"
}