{
  "uuid": "c2404d93-4aaa-4dea-bd88-a54c8d6414d4",
  "path": "/usr/lib/python3.12/test/__pycache__/test_sunau.cpython-312.pyc",
  "size": 9439,
  "modified": "2025-05-28T17:29:54.711463538Z",
  "created": "2025-05-28T17:29:54.711463538Z",
  "sha256_hash": "aa006e15311c44ceb43761570292946dbe46b7c06ded905f68168633aa8678da",
  "file_type": {
    "Other": "pyc"
  },
  "permissions": 33188,
  "is_executable": true,
  "is_signed": false,
  "code_signature": null,
  "bundle_info": null,
  "scan_timestamp": "2025-06-01T18:46:03.301737203Z"
}