{
  "uuid": "c73d905d-ecf3-4608-a1b4-b84c402c3687",
  "path": "/lib/python3.12/test/xmltestdata/c14n-20/out_inC14N2_c14nTrim.xml",
  "size": 99,
  "modified": "2025-02-04T14:48:35Z",
  "created": "2025-05-28T17:29:48.053550961Z",
  "sha256_hash": "a8218ea3d5e7bf22ea6751ca3e87c5a9f02db45eb9753025e7baa569bb0e1c62",
  "file_type": {
    "Other": "xml"
  },
  "permissions": 33188,
  "is_executable": false,
  "is_signed": false,
  "code_signature": null,
  "bundle_info": null,
  "scan_timestamp": "2025-06-01T18:47:08.280959303Z"
}