{
  "uuid": "cb5956e0-9ad7-495e-ac91-55a1a1872304",
  "path": "/lib/firmware/iwlwifi-QuZ-a0-jf-b0-66.ucode.zst",
  "size": 462853,
  "modified": "2025-04-17T06:14:44Z",
  "created": "2025-05-29T10:40:08.612540704Z",
  "sha256_hash": "d57fc12c76a9719836317065fd49570df927f2ac388e46254b7822061dc3f5e7",
  "file_type": {
    "Other": "zst"
  },
  "permissions": 33188,
  "is_executable": false,
  "is_signed": false,
  "code_signature": null,
  "bundle_info": null,
  "scan_timestamp": "2025-06-01T18:47:07.085615776Z"
}