{
  "uuid": "d725b01f-5d66-488e-a76a-cf539bc041dc",
  "path": "/lib/firmware/i915/kbl_dmc_ver1_01.bin.zst",
  "size": 2501,
  "modified": "2025-04-17T06:14:44Z",
  "created": "2025-05-29T10:40:08.540541701Z",
  "sha256_hash": "6ac934c0678deaf1d7d446398b1cc6ffacf494b2b18439239c769c939bdfa5b6",
  "file_type": {
    "Other": "zst"
  },
  "permissions": 33188,
  "is_executable": false,
  "is_signed": false,
  "code_signature": null,
  "bundle_info": null,
  "scan_timestamp": "2025-06-01T18:47:05.684279433Z"
}