{
  "uuid": "d787700e-8aac-45d5-9bd1-2c0e4e91e06f",
  "path": "/lib/gcc/x86_64-linux-gnu/13/adainclude/a-ztedit.adb",
  "size": 77232,
  "modified": "2024-05-21T07:47:38Z",
  "created": "2025-05-29T11:24:15.063344970Z",
  "sha256_hash": "1a02e708ed0431f5387352d5cce2b661b06eca64630fe3a19406d4aa62837aeb",
  "file_type": {
    "Other": "adb"
  },
  "permissions": 33188,
  "is_executable": false,
  "is_signed": false,
  "code_signature": null,
  "bundle_info": null,
  "scan_timestamp": "2025-06-01T18:46:56.902773668Z"
}