{
  "uuid": "dfc61595-1795-406b-9e18-d0674a8b9869",
  "path": "/lib/gcc/x86_64-linux-gnu/13/adainclude/s-pack94.ads",
  "size": 3895,
  "modified": "2024-05-21T07:47:38Z",
  "created": "2025-05-29T11:24:15.086344654Z",
  "sha256_hash": "156fe3829e914f27b20ef884c88ca2fc4944a4db27d025f4deb48d874f0e9b4d",
  "file_type": {
    "Other": "ads"
  },
  "permissions": 33188,
  "is_executable": false,
  "is_signed": false,
  "code_signature": null,
  "bundle_info": null,
  "scan_timestamp": "2025-06-01T18:46:56.998119624Z"
}