{
  "uuid": "e69bf588-43af-44c0-b6b0-129e2568ee19",
  "path": "/lib/python3.12/test/__pycache__/test_xxtestfuzz.cpython-312.pyc",
  "size": 1484,
  "modified": "2025-05-28T17:29:55.053459048Z",
  "created": "2025-05-28T17:29:55.053459048Z",
  "sha256_hash": "6c9ac94bda9b8a021222e3fd1e92131dfe0c7f0d247e9269bdb59c2c0235fbf3",
  "file_type": {
    "Other": "pyc"
  },
  "permissions": 33188,
  "is_executable": false,
  "is_signed": false,
  "code_signature": null,
  "bundle_info": null,
  "scan_timestamp": "2025-06-01T18:47:07.991585201Z"
}