{
  "uuid": "e9157159-5684-435d-b2d7-27a8d16eebeb",
  "path": "/usr/lib/x86_64-linux-gnu/xtables/libipt_CLUSTERIP.so",
  "size": 14784,
  "modified": "2024-04-08T15:59:59Z",
  "created": "2025-05-09T05:07:37.327631452Z",
  "sha256_hash": "347ed43323470f4647b673580e9a7c616b5ef4d36a2d8a46070f93c94acf29c4",
  "file_type": "Library",
  "permissions": 33188,
  "is_executable": true,
  "is_signed": false,
  "code_signature": null,
  "bundle_info": null,
  "scan_timestamp": "2025-06-01T18:46:21.248810069Z"
}