{
  "uuid": "e97634e4-b98b-48d9-93fb-f5b390402c89",
  "path": "/usr/lib/python3/dist-packages/uaclient/__pycache__/defaults.cpython-312.pyc",
  "size": 3938,
  "modified": "2025-05-09T05:24:41.363146316Z",
  "created": "2025-05-09T05:24:41.363146316Z",
  "sha256_hash": "af3e64f81ec4491d243b13b26d4834beaeffed4f2cf9a84b2389ae2f24ca32d9",
  "file_type": {
    "Other": "pyc"
  },
  "permissions": 33188,
  "is_executable": true,
  "is_signed": false,
  "code_signature": null,
  "bundle_info": null,
  "scan_timestamp": "2025-06-01T18:45:25.766348476Z"
}