{
  "uuid": "e9fbd3ba-fc12-4044-adbb-5249ca78b94d",
  "path": "/usr/lib/python3/dist-packages/rich/traceback.py",
  "size": 29529,
  "modified": "2024-03-04T23:07:14Z",
  "created": "2025-05-09T05:07:27.369783407Z",
  "sha256_hash": "393aed74760f30290759c39bb9f17d42dc8246f98d2ff53509728a213a7886b1",
  "file_type": "Script",
  "permissions": 33188,
  "is_executable": true,
  "is_signed": false,
  "code_signature": null,
  "bundle_info": null,
  "scan_timestamp": "2025-06-01T18:45:26.358864794Z"
}