{
  "uuid": "ec9d30ff-770d-4b2b-8080-4a8c4679e539",
  "path": "/usr/lib/gcc/x86_64-linux-gnu/13/adalib/a-convec.ali",
  "size": 44181,
  "modified": "2024-09-04T14:44:14Z",
  "created": "2025-05-29T11:24:15.097344503Z",
  "sha256_hash": "8a1ff6a9696a4d22c0b927f1cd5814cca6d4d9f9907d93eb36e0baddf108dee3",
  "file_type": {
    "Other": "ali"
  },
  "permissions": 33060,
  "is_executable": true,
  "is_signed": false,
  "code_signature": null,
  "bundle_info": null,
  "scan_timestamp": "2025-06-01T18:45:49.690564791Z"
}