{
  "uuid": "f1efb1fa-4ac4-46df-b2ba-bd3d85e97219",
  "path": "/usr/lib/gcc/x86_64-linux-gnu/13/adalib/a-crbltr.ali",
  "size": 3226,
  "modified": "2024-09-04T14:44:14Z",
  "created": "2025-05-29T11:24:15.098344489Z",
  "sha256_hash": "14f8e4b38ce2d5ab8ddb67ea0e3ed8bd2b428a81d62be9d25b249fdb004c2154",
  "file_type": {
    "Other": "ali"
  },
  "permissions": 33060,
  "is_executable": true,
  "is_signed": false,
  "code_signature": null,
  "bundle_info": null,
  "scan_timestamp": "2025-06-01T18:45:49.815009750Z"
}