{
  "uuid": "f605b2db-b8c4-46db-ad0e-15bc4ae55849",
  "path": "/lib/python3/dist-packages/babel/localtime/_win32.py",
  "size": 3086,
  "modified": "2022-06-16T05:56:23Z",
  "created": "2025-05-09T05:07:26.550795904Z",
  "sha256_hash": "746ce143c025639888b5277e8b7162d8edd85ae549f373c54967bb106d816818",
  "file_type": "Script",
  "permissions": 33188,
  "is_executable": false,
  "is_signed": false,
  "code_signature": null,
  "bundle_info": null,
  "scan_timestamp": "2025-06-01T18:46:33.776157097Z"
}