{
  "uuid": "f8692e1e-f7ab-481b-a234-d5ff7492b21c",
  "path": "/lib/x86_64-linux-gnu/espeak-ng-data/pl_dict",
  "size": 76730,
  "modified": "2024-04-08T15:56:57Z",
  "created": "2025-05-09T05:07:35.498659362Z",
  "sha256_hash": "0e0ce6cfe4eba41a1223362a046390dca359a3e597af8243adaac84d624ef18f",
  "file_type": {
    "Other": "unknown"
  },
  "permissions": 33188,
  "is_executable": false,
  "is_signed": false,
  "code_signature": null,
  "bundle_info": null,
  "scan_timestamp": "2025-06-01T18:47:24.307434324Z"
}