{
  "uuid": "f9adcfa7-3f8a-4f6d-8844-d379e6021af8",
  "path": "/lib/gcc/x86_64-linux-gnu/13/adainclude/a-ztcstr.adb",
  "size": 3827,
  "modified": "2024-05-21T07:47:38Z",
  "created": "2025-05-29T11:24:15.063344970Z",
  "sha256_hash": "92bc4f98fee49fcdd1497a36ebfcadba57f8fb88179d5a1e32c94f385d2ce1f4",
  "file_type": {
    "Other": "adb"
  },
  "permissions": 33188,
  "is_executable": false,
  "is_signed": false,
  "code_signature": null,
  "bundle_info": null,
  "scan_timestamp": "2025-06-01T18:46:56.940554792Z"
}