{
  "uuid": "fbf4021b-5ba4-4c02-8043-de0ea17616ca",
  "path": "/lib/grub/x86_64-efi/gettext.mod",
  "size": 8664,
  "modified": "2025-03-17T13:20:09Z",
  "created": "2025-05-09T05:08:37.809708445Z",
  "sha256_hash": "04f3f8237c11d74513578001ff0d1e1152824eb33e24f2d14a28ee0c8e2dd463",
  "file_type": {
    "Other": "mod"
  },
  "permissions": 33188,
  "is_executable": false,
  "is_signed": false,
  "code_signature": null,
  "bundle_info": null,
  "scan_timestamp": "2025-06-01T18:47:00.140677225Z"
}