{
  "uuid": "fc122430-b42b-4c10-86ec-83ab55e0aee1",
  "path": "/usr/lib/python3.12/lib2to3/fixes/__pycache__/fix_unicode.cpython-312.pyc",
  "size": 2159,
  "modified": "2025-05-28T17:29:55.214456934Z",
  "created": "2025-05-28T17:29:55.214456934Z",
  "sha256_hash": "e3c0ea5c3160db465c614077a1241c1e603f3b3351ba3a81d3ecf4f30cf41216",
  "file_type": {
    "Other": "pyc"
  },
  "permissions": 33188,
  "is_executable": true,
  "is_signed": false,
  "code_signature": null,
  "bundle_info": null,
  "scan_timestamp": "2025-06-01T18:46:04.903985572Z"
}