{
  "uuid": "fc34659e-56a3-4b67-9c7d-e80fce142e3b",
  "path": "/lib/python3/dist-packages/certifi/__pycache__/__main__.cpython-312.pyc",
  "size": 589,
  "modified": "2025-02-15T08:12:00Z",
  "created": "2025-05-09T05:07:26.575795523Z",
  "sha256_hash": "4de0cd7656d8f314dfeaa9f10c35caca90e3a5f63f31d3beb3a01affc7165b69",
  "file_type": {
    "Other": "pyc"
  },
  "permissions": 33188,
  "is_executable": false,
  "is_signed": false,
  "code_signature": null,
  "bundle_info": null,
  "scan_timestamp": "2025-06-01T18:46:34.036214913Z"
}