{
  "uuid": "fc4ee24a-29bd-4894-b294-1bc442b2f7ba",
  "path": "/lib/x86_64-linux-gnu/espeak-ng-data/voices/mb/mb-vz1",
  "size": 144,
  "modified": "2022-04-02T20:26:29Z",
  "created": "2025-05-09T05:07:35.586658019Z",
  "sha256_hash": "4bd9cd1244c71b583fe8279bb8c092ddaca61873ce76b19a9d78a8731b97eedc",
  "file_type": {
    "Other": "unknown"
  },
  "permissions": 33188,
  "is_executable": false,
  "is_signed": false,
  "code_signature": null,
  "bundle_info": null,
  "scan_timestamp": "2025-06-01T18:47:24.364705003Z"
}