{
  "uuid": "fc9ca4bd-df99-44ad-8850-95a325475b7f",
  "path": "/usr/lib/x86_64-linux-gnu/espeak-ng-data/si_dict",
  "size": 85384,
  "modified": "2024-04-08T15:56:57Z",
  "created": "2025-05-09T05:07:35.546658630Z",
  "sha256_hash": "a241437d4b64fd328ac4a3e786c9465c60488f6fa31cbba04153f628cdc61f27",
  "file_type": "Executable",
  "permissions": 33188,
  "is_executable": true,
  "is_signed": false,
  "code_signature": null,
  "bundle_info": null,
  "scan_timestamp": "2025-06-01T18:46:20.887377303Z"
}