{
  "uuid": "ff96833e-5c30-4c6b-b268-6e76745c7c31",
  "path": "/lib/python3.12/test/__pycache__/test_listcomps.cpython-312.pyc",
  "size": 31776,
  "modified": "2025-05-28T17:29:54.295469001Z",
  "created": "2025-05-28T17:29:54.295469001Z",
  "sha256_hash": "3a9c94a18ed3fc50c2c11b827174d846b3e385cbaa5744f53af9fba01998d056",
  "file_type": {
    "Other": "pyc"
  },
  "permissions": 33188,
  "is_executable": false,
  "is_signed": false,
  "code_signature": null,
  "bundle_info": null,
  "scan_timestamp": "2025-06-01T18:47:07.923533572Z"
}